flac_detective/__init__.py
flac_detective/__version__.py
flac_detective/analyzer.py
flac_detective/colors.py
flac_detective/config.py
flac_detective/logging_config.py
flac_detective/main.py
flac_detective/repair.py
flac_detective/reporter.py
flac_detective/tracker.py
flac_detective/utils.py
flac_detective/analysis/__init__.py
flac_detective/analysis/analyzer.py
flac_detective/analysis/audio_cache.py
flac_detective/analysis/diagnostic_tracker.py
flac_detective/analysis/file_cache.py
flac_detective/analysis/metadata.py
flac_detective/analysis/quality.py
flac_detective/analysis/scoring.py
flac_detective/analysis/spectrum.py
flac_detective/analysis/window_cache.py
flac_detective/analysis/new_scoring/__init__.py
flac_detective/analysis/new_scoring/artifacts.py
flac_detective/analysis/new_scoring/audio_loader.py
flac_detective/analysis/new_scoring/bitrate.py
flac_detective/analysis/new_scoring/calculator.py
flac_detective/analysis/new_scoring/constants.py
flac_detective/analysis/new_scoring/metadata.py
flac_detective/analysis/new_scoring/models.py
flac_detective/analysis/new_scoring/silence.py
flac_detective/analysis/new_scoring/silence_utils.py
flac_detective/analysis/new_scoring/strategies.py
flac_detective/analysis/new_scoring/verdict.py
flac_detective/analysis/new_scoring/rules/__init__.py
flac_detective/analysis/new_scoring/rules/artifacts.py
flac_detective/analysis/new_scoring/rules/bitrate.py
flac_detective/analysis/new_scoring/rules/cassette.py
flac_detective/analysis/new_scoring/rules/consistency.py
flac_detective/analysis/new_scoring/rules/silence.py
flac_detective/analysis/new_scoring/rules/spectral.py
flac_detective/repair/__init__.py
flac_detective/repair/__main__.py
flac_detective/repair/encoding.py
flac_detective/repair/fixer.py
flac_detective/repair/metadata.py
flac_detective/reporting/__init__.py
flac_detective/reporting/statistics.py
flac_detective/reporting/text_reporter.py
flac_detective-0.9.6.dist-info/licenses/LICENSE
flac_detective-0.9.6.dist-info/METADATA
flac_detective-0.9.6.dist-info/WHEEL
flac_detective-0.9.6.dist-info/entry_points.txt
flac_detective-0.9.6.dist-info/top_level.txt
flac_detective-0.9.6.dist-info/RECORD
